aegis/__init__.py
aegis/approvals.py
aegis/logging.py
aegis/rules.py
aegis/wrapper.py
aegis_agent-1.0.4.dist-info/licenses/LICENSE
aegis_agent-1.0.4.dist-info/METADATA
aegis_agent-1.0.4.dist-info/WHEEL
aegis_agent-1.0.4.dist-info/top_level.txt
aegis_agent-1.0.4.dist-info/RECORD
