Metadata-Version: 2.4
Name: aegis-agent
Version: 1.0.4
Summary: Human-in-the-loop control layer for AI agents
Author: Aegis Contributors
License: MIT
Project-URL: Homepage, https://github.com/yourusername/aegis-core
Project-URL: Repository, https://github.com/yourusername/aegis-core
Project-URL: Issues, https://github.com/yourusername/aegis-core/issues
Keywords: ai,agents,langchain,human-in-the-loop,safety,control
Classifier: Development Status :: 4 - Beta
Classifier: Intended Audience :: Developers
Classifier: License :: OSI Approved :: MIT License
Classifier: Programming Language :: Python :: 3
Classifier: Programming Language :: Python :: 3.7
Classifier: Programming Language :: Python :: 3.8
Classifier: Programming Language :: Python :: 3.9
Classifier: Programming Language :: Python :: 3.10
Classifier: Programming Language :: Python :: 3.11
Classifier: Topic :: Software Development :: Libraries :: Python Modules
Classifier: Topic :: Scientific/Engineering :: Artificial Intelligence
Requires-Python: >=3.7
License-File: LICENSE
Requires-Dist: fastapi>=0.68.0
Requires-Dist: uvicorn>=0.15.0
Provides-Extra: dev
Dynamic: license-file
